text_to_speech_api-2025.0.2.dist-info/METADATA
text_to_speech_api-2025.0.2.dist-info/WHEEL
text_to_speech_api-2025.0.2.dist-info/entry_points.txt
text_to_speech_api/__init__.py
text_to_speech_api-2025.0.2.dist-info/RECORD
