Metadata-Version: 2.1
Name: text_to_speech_api
Version: 2025.0.2
Summary: image-upscaling.net api client
Keywords: tts,text-to-speech,ai,voice synthesis,speech generation,python-api,free-tts,machine-learning,deep-learning,audio,speech
Author: Marvin Eckhardt
Maintainer: Marvin Eckhardt
Classifier: Programming Language :: Python
Classifier: License :: OSI Approved :: MIT License
Classifier: Topic :: Multimedia :: Sound/Audio :: Speech
Classifier: Topic :: Scientific/Engineering :: Artificial Intelligence
Classifier: Topic :: Software Development :: Libraries :: Python Modules
Project-URL: Homepage, https://image-upscaling.net/online_tts
Requires-Python: >=3.8
Requires-Dist: requests
